{
    "info":  {
                 "name":  "FIT4110 Lab03 - Team Gate Collection",
                 "schema":  "https://schema.getpostman.com/json/collection/v2.1.0/collection.json",
                 "description":  "Integration tests for team-gate Access Gate service."
             },
    "auth":  {
                 "type":  "bearer",
                 "bearer":  [
                                {
                                    "key":  "token",
                                    "value":  "{{authToken}}",
                                    "type":  "string"
                                }
                            ]
             },
    "item":  [
                 {
                     "name":  "01_Functional",
                     "item":  [
                                  {
                                      "name":  "GET Health",
                                      "event":  [
                                                    {
                                                        "listen":  "test",
                                                        "script":  {
                                                                       "type":  "text/javascript",
                                                                       "exec":  [
                                                                                    "pm.test(\u0027Expected status 200\u0027, function () {",
                                                                                    "  pm.response.to.have.status(200);",
                                                                                    "});"
                                                                                ]
                                                                   }
                                                    }
                                                ],
                                      "request":  {
                                                      "auth":  {
                                                                   "type":  "noauth"
                                                               },
                                                      "method":  "GET",
                                                      "url":  "{{baseUrl}}/health"
                                                  }
                                  },
                                  {
                                      "name":  "POST Create Access Event Valid",
                                      "event":  [
                                                    {
                                                        "listen":  "test",
                                                        "script":  {
                                                                       "type":  "text/javascript",
                                                                       "exec":  [
                                                                                    "pm.test(\u0027Expected status 201 or 200\u0027, function () {",
                                                                                    "  pm.expect([200, 201]).to.include(pm.response.code);",
                                                                                    "});",
                                                                                    "pm.test(\u0027Response has eventId\u0027, function () {",
                                                                                    "  const json = pm.response.json();",
                                                                                    "  pm.expect(json).to.have.property(\u0027eventId\u0027);",
                                                                                    "  pm.expect(json.eventId).to.be.a(\u0027string\u0027).and.not.empty;",
                                                                                    "  pm.environment.set(\u0027eventId\u0027, json.eventId);",
                                                                                    "});"
                                                                                ]
                                                                   }
                                                    }
                                                ],
                                      "request":  {
                                                      "method":  "POST",
                                                      "header":  [
                                                                     {
                                                                         "key":  "Content-Type",
                                                                         "value":  "application/json"
                                                                     },
                                                                     {
                                                                         "key":  "Authorization",
                                                                         "value":  "Bearer {{authToken}}"
                                                                     }
                                                                 ],
                                                      "body":  {
                                                                   "mode":  "raw",
                                                                   "raw":  "{\n  \"personId\": \"SV001\",\n  \"gateId\": \"{{gateId}}\",\n  \"credentialId\": \"{{credentialId}}\",\n  \"decision\": \"allow\",\n  \"reason\": \"valid_credential\",\n  \"riskLevel\": \"low\",\n  \"eventTime\": \"2026-05-27T08:00:00Z\",\n  \"location\": \"Building A - Main Gate\"\n}"
                                                               },
                                                      "url":  "{{baseUrl}}/access-events"
                                                  }
                                  },
                                  {
                                      "name":  "POST Create Access Decision Allow",
                                      "event":  [
                                                    {
                                                        "listen":  "test",
                                                        "script":  {
                                                                       "type":  "text/javascript",
                                                                       "exec":  [
                                                                                    "pm.test(\u0027Expected status 200 or 201\u0027, function () {",
                                                                                    "  pm.expect([200, 201]).to.include(pm.response.code);",
                                                                                    "});",
                                                                                    "pm.test(\u0027Response has decision\u0027, function () {",
                                                                                    "  const json = pm.response.json();",
                                                                                    "  pm.expect(json).to.have.property(\u0027decision\u0027);",
                                                                                    "});",
                                                                                    "pm.test(\u0027decision is allow or deny\u0027, function () {",
                                                                                    "  const json = pm.response.json();",
                                                                                    "  pm.expect([\u0027allow\u0027, \u0027deny\u0027]).to.include(json.decision);",
                                                                                    "});"
                                                                                ]
                                                                   }
                                                    }
                                                ],
                                      "request":  {
                                                      "method":  "POST",
                                                      "header":  [
                                                                     {
                                                                         "key":  "Content-Type",
                                                                         "value":  "application/json"
                                                                     },
                                                                     {
                                                                         "key":  "Authorization",
                                                                         "value":  "Bearer {{authToken}}"
                                                                     }
                                                                 ],
                                                      "body":  {
                                                                   "mode":  "raw",
                                                                   "raw":  "{\n  \"eventId\": \"{{eventId}}\",\n  \"personId\": \"SV001\",\n  \"gateId\": \"{{gateId}}\",\n  \"credentialId\": \"{{credentialId}}\",\n  \"decision\": \"allow\",\n  \"reason\": \"policy_matched\",\n  \"riskLevel\": \"low\",\n  \"eventTime\": \"2026-05-27T08:00:01Z\",\n  \"location\": \"Building A - Main Gate\"\n}"
                                                               },
                                                      "url":  "{{baseUrl}}/access-decisions"
                                                  }
                                  },
                                  {
                                      "name":  "GET Access Event By Id",
                                      "event":  [
                                                    {
                                                        "listen":  "test",
                                                        "script":  {
                                                                       "type":  "text/javascript",
                                                                       "exec":  [
                                                                                    "pm.test(\u0027Expected status 200\u0027, function () {",
                                                                                    "  pm.response.to.have.status(200);",
                                                                                    "});",
                                                                                    "pm.test(\u0027Response has event information\u0027, function () {",
                                                                                    "  const json = pm.response.json();",
                                                                                    "  pm.expect(json).to.have.property(\u0027eventId\u0027);",
                                                                                    "  pm.expect(json).to.have.property(\u0027gateId\u0027);",
                                                                                    "  pm.expect(json).to.have.property(\u0027credentialId\u0027);",
                                                                                    "  pm.expect(json).to.have.property(\u0027eventTime\u0027);",
                                                                                    "});"
                                                                                ]
                                                                   }
                                                    }
                                                ],
                                      "request":  {
                                                      "method":  "GET",
                                                      "header":  [
                                                                     {
                                                                         "key":  "Authorization",
                                                                         "value":  "Bearer {{authToken}}"
                                                                     }
                                                                 ],
                                                      "url":  "{{baseUrl}}/access-events/{{eventId}}"
                                                  }
                                  }
                              ]
                 },
                 {
                     "name":  "02_Auth",
                     "item":  [
                                  {
                                      "name":  "Auth - Valid Token",
                                      "event":  [
                                                    {
                                                        "listen":  "test",
                                                        "script":  {
                                                                       "type":  "text/javascript",
                                                                       "exec":  [
                                                                                    "pm.test(\u0027Expected status 200 or 201\u0027, function () {",
                                                                                    "  pm.expect([200, 201]).to.include(pm.response.code);",
                                                                                    "});"
                                                                                ]
                                                                   }
                                                    }
                                                ],
                                      "request":  {
                                                      "method":  "GET",
                                                      "header":  [
                                                                     {
                                                                         "key":  "Authorization",
                                                                         "value":  "Bearer {{authToken}}"
                                                                     }
                                                                 ],
                                                      "url":  "{{baseUrl}}/access-events/latest?limit=10"
                                                  }
                                  },
                                  {
                                      "name":  "Auth - Missing Token",
                                      "event":  [
                                                    {
                                                        "listen":  "test",
                                                        "script":  {
                                                                       "type":  "text/javascript",
                                                                       "exec":  [
                                                                                    "pm.test(\u0027Expected status 401 or 403 when missing token\u0027, function () {",
                                                                                    "  pm.expect([401, 403]).to.include(pm.response.code);",
                                                                                    "});"
                                                                                ]
                                                                   }
                                                    }
                                                ],
                                      "request":  {
                                                      "auth":  {
                                                                   "type":  "noauth"
                                                               },
                                                      "method":  "GET",
                                                      "url":  "{{baseUrl}}/access-events/latest?limit=10"
                                                  }
                                  },
                                  {
                                      "name":  "Auth - Invalid Token",
                                      "event":  [
                                                    {
                                                        "listen":  "test",
                                                        "script":  {
                                                                       "type":  "text/javascript",
                                                                       "exec":  [
                                                                                    "const env = pm.environment.get(\u0027env\u0027);",
                                                                                    "if (env === \u0027mock\u0027) {",
                                                                                    "  pm.test(\u0027Mock accepts non-enforced auth behavior\u0027, function () {",
                                                                                    "    pm.expect([200, 401, 403]).to.include(pm.response.code);",
                                                                                    "  });",
                                                                                    "} else {",
                                                                                    "  pm.test(\u0027Local rejects invalid token\u0027, function () {",
                                                                                    "    pm.expect([401, 403]).to.include(pm.response.code);",
                                                                                    "  });",
                                                                                    "}"
                                                                                ]
                                                                   }
                                                    }
                                                ],
                                      "request":  {
                                                      "auth":  {
                                                                   "type":  "noauth"
                                                               },
                                                      "method":  "GET",
                                                      "header":  [
                                                                     {
                                                                         "key":  "Authorization",
                                                                         "value":  "Bearer invalid-token"
                                                                     }
                                                                 ],
                                                      "url":  "{{baseUrl}}/access-events/latest?limit=10"
                                                  }
                                  }
                              ]
                 },
                 {
                     "name":  "03_Negative",
                     "item":  [
                                  {
                                      "name":  "Negative - Missing credentialId",
                                      "event":  [
                                                    {
                                                        "listen":  "test",
                                                        "script":  {
                                                                       "type":  "text/javascript",
                                                                       "exec":  [
                                                                                    "pm.test(\u0027Expected status 400 or 422\u0027, function () {",
                                                                                    "  pm.expect([400, 422]).to.include(pm.response.code);",
                                                                                    "});",
                                                                                    "pm.test(\u0027Server returns ProblemDetails-like error\u0027, function () {",
                                                                                    "  const json = pm.response.json();",
                                                                                    "  pm.expect(json).to.have.property(\u0027status\u0027);",
                                                                                    "  pm.expect(json.status).to.be.within(400, 599);",
                                                                                    "  pm.expect(json).to.have.property(\u0027title\u0027);",
                                                                                    "});"
                                                                                ]
                                                                   }
                                                    }
                                                ],
                                      "request":  {
                                                      "method":  "POST",
                                                      "header":  [
                                                                     {
                                                                         "key":  "Content-Type",
                                                                         "value":  "application/json"
                                                                     },
                                                                     {
                                                                         "key":  "Authorization",
                                                                         "value":  "Bearer {{authToken}}"
                                                                     }
                                                                 ],
                                                      "body":  {
                                                                   "mode":  "raw",
                                                                   "raw":  "{\n  \"eventId\": \"{{eventId}}\",\n  \"personId\": \"SV001\",\n  \"gateId\": \"{{gateId}}\",\n  \"decision\": \"allow\",\n  \"reason\": \"policy_matched\",\n  \"riskLevel\": \"low\",\n  \"eventTime\": \"2026-05-27T08:00:01Z\",\n  \"location\": \"Building A - Main Gate\"\n}"
                                                               },
                                                      "url":  "{{baseUrl}}/access-decisions"
                                                  }
                                  },
                                  {
                                      "name":  "Negative - Invalid gateId",
                                      "event":  [
                                                    {
                                                        "listen":  "test",
                                                        "script":  {
                                                                       "type":  "text/javascript",
                                                                       "exec":  [
                                                                                    "pm.test(\u0027Expected status 400, 404, or 422\u0027, function () {",
                                                                                    "  pm.expect([400, 404, 422]).to.include(pm.response.code);",
                                                                                    "});",
                                                                                    "pm.test(\u0027Server error response is meaningful\u0027, function () {",
                                                                                    "  const json = pm.response.json();",
                                                                                    "  pm.expect(json).to.have.property(\u0027status\u0027);",
                                                                                    "  pm.expect(json.status).to.be.within(400, 599);",
                                                                                    "  pm.expect(json).to.have.property(\u0027detail\u0027);",
                                                                                    "});"
                                                                                ]
                                                                   }
                                                    }
                                                ],
                                      "request":  {
                                                      "method":  "POST",
                                                      "header":  [
                                                                     {
                                                                         "key":  "Content-Type",
                                                                         "value":  "application/json"
                                                                     },
                                                                     {
                                                                         "key":  "Authorization",
                                                                         "value":  "Bearer {{authToken}}"
                                                                     }
                                                                 ],
                                                      "body":  {
                                                                   "mode":  "raw",
                                                                   "raw":  "{\n  \"eventId\": \"{{eventId}}\",\n  \"personId\": \"SV001\",\n  \"gateId\": \"INVALID_GATE\",\n  \"credentialId\": \"{{credentialId}}\",\n  \"decision\": \"allow\",\n  \"reason\": \"policy_matched\",\n  \"riskLevel\": \"low\",\n  \"eventTime\": \"2026-05-27T08:00:01Z\",\n  \"location\": \"Building A - Main Gate\"\n}"
                                                               },
                                                      "url":  "{{baseUrl}}/access-decisions"
                                                  }
                                  },
                                  {
                                      "name":  "Negative - Invalid payload type",
                                      "event":  [
                                                    {
                                                        "listen":  "test",
                                                        "script":  {
                                                                       "type":  "text/javascript",
                                                                       "exec":  [
                                                                                    "pm.test(\u0027Expected status 400 or 422\u0027, function () {",
                                                                                    "  pm.expect([400, 422]).to.include(pm.response.code);",
                                                                                    "});",
                                                                                    "pm.test(\u0027Server validates payload type\u0027, function () {",
                                                                                    "  const json = pm.response.json();",
                                                                                    "  pm.expect(json).to.have.property(\u0027status\u0027);",
                                                                                    "  pm.expect(json.status).to.be.within(400, 599);",
                                                                                    "  pm.expect(json).to.have.property(\u0027title\u0027);",
                                                                                    "});"
                                                                                ]
                                                                   }
                                                    }
                                                ],
                                      "request":  {
                                                      "method":  "POST",
                                                      "header":  [
                                                                     {
                                                                         "key":  "Content-Type",
                                                                         "value":  "application/json"
                                                                     },
                                                                     {
                                                                         "key":  "Authorization",
                                                                         "value":  "Bearer {{authToken}}"
                                                                     }
                                                                 ],
                                                      "body":  {
                                                                   "mode":  "raw",
                                                                   "raw":  "{\n  \"eventId\": \"{{eventId}}\",\n  \"personId\": \"SV001\",\n  \"gateId\": \"{{gateId}}\",\n  \"credentialId\": \"{{credentialId}}\",\n  \"decision\": \"allow\",\n  \"reason\": \"policy_matched\",\n  \"riskLevel\": \"low\",\n  \"eventTime\": 1716796800,\n  \"location\": \"Building A - Main Gate\"\n}"
                                                               },
                                                      "url":  "{{baseUrl}}/access-decisions"
                                                  }
                                  },
                                  {
                                      "name":  "Negative - Unknown card or invalid card",
                                      "event":  [
                                                    {
                                                        "listen":  "test",
                                                        "script":  {
                                                                       "type":  "text/javascript",
                                                                       "exec":  [
                                                                                    "const env = pm.environment.get(\u0027env\u0027);",
                                                                                    "if (env === \u0027mock\u0027) {",
                                                                                    "  pm.test(\u0027Mock behavior for invalid card is accepted\u0027, function () {",
                                                                                    "    pm.expect([201, 403, 404, 422]).to.include(pm.response.code);",
                                                                                    "  });",
                                                                                    "} else {",
                                                                                    "  pm.test(\u0027Local must reject invalid card\u0027, function () {",
                                                                                    "    pm.expect([403, 404, 422]).to.include(pm.response.code);",
                                                                                    "  });",
                                                                                    "}",
                                                                                    "pm.test(\u0027Response includes rejection reason or ProblemDetails (when provided)\u0027, function () {",
                                                                                    "  let json = {};",
                                                                                    "  try { json = pm.response.json(); } catch (e) { json = {}; }",
                                                                                    "  if ([403,404,422].includes(pm.response.code)) {",
                                                                                    "    const hasProblem = Object.prototype.hasOwnProperty.call(json, \u0027status\u0027) || Object.prototype.hasOwnProperty.call(json, \u0027title\u0027);",
                                                                                    "    const hasReason = Object.prototype.hasOwnProperty.call(json, \u0027reason\u0027) || Object.prototype.hasOwnProperty.call(json, \u0027reasonCode\u0027);",
                                                                                    "    pm.expect(hasProblem || hasReason).to.eql(true);",
                                                                                    "  } else {",
                                                                                    "    pm.expect(pm.environment.get(\u0027env\u0027)).to.eql(\u0027mock\u0027);",
                                                                                    "  }",
                                                                                    "});"
                                                                                ]
                                                                   }
                                                    }
                                                ],
                                      "request":  {
                                                      "method":  "POST",
                                                      "header":  [
                                                                     {
                                                                         "key":  "Content-Type",
                                                                         "value":  "application/json"
                                                                     },
                                                                     {
                                                                         "key":  "Authorization",
                                                                         "value":  "Bearer {{authToken}}"
                                                                     }
                                                                 ],
                                                      "body":  {
                                                                   "mode":  "raw",
                                                                   "raw":  "{\n  \"eventId\": \"{{eventId}}\",\n  \"personId\": \"SV001\",\n  \"gateId\": \"{{gateId}}\",\n  \"credentialId\": \"INVALID-CARD-999\",\n  \"decision\": \"deny\",\n  \"reason\": \"invalid_credential\",\n  \"riskLevel\": \"medium\",\n  \"eventTime\": \"2026-05-27T08:00:01Z\",\n  \"location\": \"Building A - Main Gate\"\n}"
                                                               },
                                                      "url":  "{{baseUrl}}/access-decisions"
                                                  }
                                  }
                              ]
                 },
                 {
                     "name":  "04_Boundary_Reliability",
                     "item":  [
                                  {
                                      "name":  "Boundary - riskLevel high behavior",
                                      "event":  [
                                                    {
                                                        "listen":  "test",
                                                        "script":  {
                                                                       "type":  "text/javascript",
                                                                       "exec":  [
                                                                                    "pm.test(\u0027Status matches documented behavior for high risk\u0027, function () {",
                                                                                    "  pm.expect([200, 201, 400, 422]).to.include(pm.response.code);",
                                                                                    "});",
                                                                                    "pm.test(\u0027Response has clear rule outcome\u0027, function () {",
                                                                                    "  const json = pm.response.json();",
                                                                                    "  if ([200, 201].includes(pm.response.code)) {",
                                                                                    "    const hasReason = Object.prototype.hasOwnProperty.call(json, \u0027reason\u0027) || Object.prototype.hasOwnProperty.call(json, \u0027reasonCode\u0027);",
                                                                                    "    const hasWarningHeader = pm.response.headers.has(\u0027X-Warning\u0027);",
                                                                                    "    pm.expect(hasReason || hasWarningHeader).to.eql(true);",
                                                                                    "  } else {",
                                                                                    "    pm.expect(json).to.have.property(\u0027status\u0027);",
                                                                                    "    pm.expect(json.status).to.be.within(400, 599);",
                                                                                    "    pm.expect(json).to.have.property(\u0027detail\u0027);",
                                                                                    "  }",
                                                                                    "});"
                                                                                ]
                                                                   }
                                                    }
                                                ],
                                      "request":  {
                                                      "method":  "POST",
                                                      "header":  [
                                                                     {
                                                                         "key":  "Content-Type",
                                                                         "value":  "application/json"
                                                                     },
                                                                     {
                                                                         "key":  "Authorization",
                                                                         "value":  "Bearer {{authToken}}"
                                                                     }
                                                                 ],
                                                      "body":  {
                                                                   "mode":  "raw",
                                                                   "raw":  "{\n  \"eventId\": \"{{eventId}}\",\n  \"personId\": \"SV001\",\n  \"gateId\": \"{{gateId}}\",\n  \"credentialId\": \"{{credentialId}}\",\n  \"decision\": \"deny\",\n  \"reason\": \"risk_blocked\",\n  \"riskLevel\": \"high\",\n  \"eventTime\": \"2026-05-27T09:00:00Z\",\n  \"location\": \"Building A - Main Gate\"\n}"
                                                               },
                                                      "url":  "{{baseUrl}}/access-decisions"
                                                  }
                                  },
                                  {
                                      "name":  "Boundary - credentialId too long",
                                      "event":  [
                                                    {
                                                        "listen":  "test",
                                                        "script":  {
                                                                       "type":  "text/javascript",
                                                                       "exec":  [
                                                                                    "pm.test(\u0027Expected status 400 or 422 for too-long credentialId\u0027, function () {",
                                                                                    "  pm.expect([400, 422]).to.include(pm.response.code);",
                                                                                    "});",
                                                                                    "pm.test(\u0027Validation error detail is returned\u0027, function () {",
                                                                                    "  const json = pm.response.json();",
                                                                                    "  pm.expect(json).to.have.property(\u0027status\u0027);",
                                                                                    "  pm.expect(json.status).to.be.within(400, 599);",
                                                                                    "  pm.expect(json).to.have.property(\u0027detail\u0027);",
                                                                                    "});"
                                                                                ]
                                                                   }
                                                    }
                                                ],
                                      "request":  {
                                                      "method":  "POST",
                                                      "header":  [
                                                                     {
                                                                         "key":  "Content-Type",
                                                                         "value":  "application/json"
                                                                     },
                                                                     {
                                                                         "key":  "Authorization",
                                                                         "value":  "Bearer {{authToken}}"
                                                                     }
                                                                 ],
                                                      "body":  {
                                                                   "mode":  "raw",
                                                                   "raw":  "{\n  \"eventId\": \"{{eventId}}\",\n  \"personId\": \"SV001\",\n  \"gateId\": \"{{gateId}}\",\n  \"credentialId\": \"CREDENTIAL-THIS-IS-INTENTIONALLY-TOO-LONG-1234567890-ABCDEFGHIJ-KLMNOPQRST-UVWXYZ-EXTRA-LIMIT-OVER-100\",\n  \"decision\": \"allow\",\n  \"reason\": \"policy_matched\",\n  \"riskLevel\": \"low\",\n  \"eventTime\": \"2026-05-27T09:01:00Z\",\n  \"location\": \"Building A - Main Gate\"\n}"
                                                               },
                                                      "url":  "{{baseUrl}}/access-decisions"
                                                  }
                                  },
                                  {
                                      "name":  "Boundary - gateId at max length edge",
                                      "event":  [
                                                    {
                                                        "listen":  "test",
                                                        "script":  {
                                                                       "type":  "text/javascript",
                                                                       "exec":  [
                                                                                    "pm.test(\u0027Status follows boundary rule for gateId length\u0027, function () {",
                                                                                    "  pm.expect([200, 201, 400, 422]).to.include(pm.response.code);",
                                                                                    "});",
                                                                                    "pm.test(\u0027Server response is meaningful\u0027, function () {",
                                                                                    "  const json = pm.response.json();",
                                                                                    "  if ([200, 201].includes(pm.response.code)) {",
                                                                                    "    pm.expect(json).to.have.property(\u0027gateId\u0027);",
                                                                                    "  } else {",
                                                                                    "    pm.expect(json).to.have.property(\u0027status\u0027);",
                                                                                    "    pm.expect(json.status).to.be.within(400, 599);",
                                                                                    "  }",
                                                                                    "});"
                                                                                ]
                                                                   }
                                                    }
                                                ],
                                      "request":  {
                                                      "method":  "POST",
                                                      "header":  [
                                                                     {
                                                                         "key":  "Content-Type",
                                                                         "value":  "application/json"
                                                                     },
                                                                     {
                                                                         "key":  "Authorization",
                                                                         "value":  "Bearer {{authToken}}"
                                                                     }
                                                                 ],
                                                      "body":  {
                                                                   "mode":  "raw",
                                                                   "raw":  "{\n  \"eventId\": \"{{eventId}}\",\n  \"personId\": \"SV001\",\n  \"gateId\": \"gate-aaaaaaaaaaaaaaaaaaaaaaaaaaaaaaaaaaaaaaaaaaaaaaaaaaaaaaaaaaaa\",\n  \"credentialId\": \"{{credentialId}}\",\n  \"decision\": \"allow\",\n  \"reason\": \"policy_matched\",\n  \"riskLevel\": \"low\",\n  \"eventTime\": \"2026-05-27T09:02:00Z\",\n  \"location\": \"Building A - Main Gate\"\n}"
                                                               },
                                                      "url":  "{{baseUrl}}/access-decisions"
                                                  }
                                  },
                                  {
                                      "name":  "Reliability - rate limit probe",
                                      "event":  [
                                                    {
                                                        "listen":  "test",
                                                        "script":  {
                                                                       "type":  "text/javascript",
                                                                       "exec":  [
                                                                                    "pm.test(\u0027Rate limit behavior is observable\u0027, function () {",
                                                                                    "  pm.expect([200, 201, 400, 401, 403, 404, 422, 429]).to.include(pm.response.code);",
                                                                                    "});",
                                                                                    "pm.test(\u0027If 429 appears, response includes error details\u0027, function () {",
                                                                                    "  if (pm.response.code === 429) {",
                                                                                    "    const json = pm.response.json();",
                                                                                    "    pm.expect(json).to.have.property(\u0027status\u0027);",
                                                                                    "    pm.expect(json.status).to.eql(429);",
                                                                                    "    pm.expect(json).to.have.property(\u0027title\u0027);",
                                                                                    "  } else {",
                                                                                    "    pm.expect(pm.response.code).to.not.eql(500);",
                                                                                    "  }",
                                                                                    "});"
                                                                                ]
                                                                   }
                                                    }
                                                ],
                                      "request":  {
                                                      "method":  "GET",
                                                      "header":  [
                                                                     {
                                                                         "key":  "Authorization",
                                                                         "value":  "Bearer {{authToken}}"
                                                                     }
                                                                 ],
                                                      "url":  "{{baseUrl}}/access-events/latest?limit=1"
                                                  }
                                  }
                              ]
                 },
                 {
                     "name":  "05_Consumer_side_Smoke",
                     "item":  [
                                  {
                                      "name":  "Smoke - Access Gate can call dependency health endpoint",
                                      "event":  [
                                                    {
                                                        "listen":  "test",
                                                        "script":  {
                                                                       "type":  "text/javascript",
                                                                       "exec":  [
                                                                                    "pm.test(\u0027Status code is 2xx\u0027, function () {",
                                                                                    "  pm.expect(pm.response.code).to.be.within(200, 299);",
                                                                                    "});",
                                                                                    "pm.test(\u0027Response has minimum health fields\u0027, function () {",
                                                                                    "  const json = pm.response.json();",
                                                                                    "  pm.expect(json).to.have.property(\u0027status\u0027);",
                                                                                    "  pm.expect(json).to.have.property(\u0027service\u0027);",
                                                                                    "});"
                                                                                ]
                                                                   }
                                                    }
                                                ],
                                      "request":  {
                                                      "method":  "GET",
                                                      "header":  [
                                                                     {
                                                                         "key":  "Authorization",
                                                                         "value":  "Bearer {{authToken}}"
                                                                     }
                                                                 ],
                                                      "url":  "{{coreMockUrl}}/health"
                                                  }
                                  }
                              ]
                 },
                 {
                     "name":  "06_Local_only_NonFunctional",
                     "item":  [
                                  {
                                      "name":  "Local-only - access decisions latency check",
                                      "event":  [
                                                    {
                                                        "listen":  "test",
                                                        "script":  {
                                                                       "type":  "text/javascript",
                                                                       "exec":  [
                                                                                    "if (pm.environment.get(\u0027env\u0027) === \u0027local\u0027) {",
                                                                                    "  pm.test(\u0027Response time is below 1000ms on local service\u0027, function () {",
                                                                                    "    pm.expect(pm.response.responseTime).to.be.below(1000);",
                                                                                    "  });",
                                                                                    "} else {",
                                                                                    "  pm.test(\u0027Latency assertion skipped outside local environment\u0027, function () {",
                                                                                    "    pm.expect(pm.environment.get(\u0027env\u0027)).to.not.eql(\u0027local\u0027);",
                                                                                    "  });",
                                                                                    "}"
                                                                                ]
                                                                   }
                                                    }
                                                ],
                                      "request":  {
                                                      "method":  "POST",
                                                      "header":  [
                                                                     {
                                                                         "key":  "Content-Type",
                                                                         "value":  "application/json"
                                                                     },
                                                                     {
                                                                         "key":  "Authorization",
                                                                         "value":  "Bearer {{authToken}}"
                                                                     }
                                                                 ],
                                                      "body":  {
                                                                   "mode":  "raw",
                                                                   "raw":  "{\n  \"eventId\": \"{{eventId}}\",\n  \"personId\": \"SV001\",\n  \"gateId\": \"{{gateId}}\",\n  \"credentialId\": \"{{credentialId}}\",\n  \"decision\": \"allow\",\n  \"reason\": \"policy_matched\",\n  \"riskLevel\": \"low\",\n  \"eventTime\": \"2026-05-27T10:00:00Z\",\n  \"location\": \"Building A - Main Gate\"\n}"
                                                               },
                                                      "url":  "{{baseUrl}}/access-decisions"
                                                  }
                                  }
                              ]
                 }
             ]
}
